rrparser/Parser.py
rrparser/__init__.py
rrparser/__main__.py
rrparser/infos.py
rrparser-2.0.5.dist-info/LICENSE
rrparser-2.0.5.dist-info/METADATA
rrparser-2.0.5.dist-info/WHEEL
rrparser-2.0.5.dist-info/top_level.txt
rrparser-2.0.5.dist-info/RECORD
