Metadata-Version: 2.1
Name: rrparser
Version: 2.0.5
Summary: Reaction Rules Parser
Home-page: https://github.com/brsynth/RRulesParser
Author: Thomas Duigou, Melchior du Lac, Joan Hérisson
Author-email: joan.herisson@univ-evry.fr
License: MIT
Platform: UNKNOWN
Classifier: Programming Language :: Python :: 3
Classifier: License :: OSI Approved :: MIT License
Classifier: Operating System :: OS Independent
Requires-Python: >=3.5
Requires-Dist: brs-utils
